dci_utils/__init__.py
dci_utils/cloudwatch.py
dci_utils/etlrunner.py
dci_utils/pagerduty_alert.py
dci_utils/redis_connection.py
dci_utils-0.0.1148.dist-info/LICENSE
dci_utils-0.0.1148.dist-info/METADATA
dci_utils-0.0.1148.dist-info/WHEEL
dci_utils-0.0.1148.dist-info/top_level.txt
dci_utils-0.0.1148.dist-info/RECORD
